[
    {
        "name": "theme_info",
        "theme_name": "Liberty",
        "theme_version": "1.0.0",
        "theme_author": "Shopify",
        "theme_documentation_url": "https:\/\/docs.shopify.com\/manual\/more\/official-shopify-themes\/minimal",
        "theme_support_url": "https:\/\/support.shopify.com\/"
    },
    {
        "name": {
            "en": "Layout",
            "ja": "レイアウト"
        },
        "settings": [
            {
                "type": "checkbox",
                "id": "enable_wide_layout",
                "label": {
                    "en": "Enable wide layout",
                    "ja": "ワイドレイアウトを有効にする"
                }
            }
        ]
    },
    {
        "name": {
            "en": "Color",
            "ja": "色"
        },
        "settings": [
            {
                "type":"header",
                "content": {
                    "en": "Background",
                    "ja":"背景"
                }
            },
            {
                "type":"color",
                "id":"color_banner_bg",
                "default": "#2E2E2E",
                "label": {
                    "en": "Banner Color",
                    "ja": "バナーの背景"
                }
            },
            {
                "type":"color",
                "id": "color_topbar_bg",
                "default": "#FFFFFF",
                "label": {
                    "en": "Header Color",
                    "ja":"ヘッダーの背景"
                }
            },
            {
                "type":"color",
                "id":"color_main_bg",
                "default":"#FFFFFF",
                "label": {
                    "en": "Main Background Color",
                    "ja": "本文の背景"
                }
            },
            {
                "type": "color",
                "id":"color_footer_bg",
                "default":"#E0FBFF",
                "label": {
                    "en": "Footer Color",
                    "ja": "フッターの背景"
                }
            },
            {
                "type": "color",
                "id":"color_footer_under_bg",
                "default":"#2E2E2E",
                "label": {
                    "en": "Footer Under Color",
                    "ja": "フッター下部の背景"
                }
            },
            {
                "type":"header",
                "content": {
                    "en": "Text",
                    "ja":"テキスト"
                }
            },
            {
                "type": "color",
                "id": "color_banner_text",
                "default": "#FFFFFF",
                "label": {
                    "en": "Banner Text Color",
                    "ja": "バナーテキスト"
                }
            },
            {
                "type": "color",
                "id": "color_shop_text",
                "default": "#FFFFFF",
                "label": {
                    "en": "Header Shop Color",
                    "ja": "ヘッダーショップテキスト"
                }
            },
            {
                "type":"color",
                "id": "color_header_text",
                "default": "#000000",
                "label": {
                    "en": "Header Text Color",
                    "ja": "ヘッダーテキスト"
                }
            },
            {
                "type":"color",
                "id": "color_header_icon",
                "default": "#000000",
                "label": {
                    "en": "Header Icon Color",
                    "ja": "ヘッダーアイコン"
                }
            }

        ]
    }

]
